rabx/__init__.py
rabx/error.py
rabx-1.0.dist-info/DESCRIPTION.rst
rabx-1.0.dist-info/METADATA
rabx-1.0.dist-info/metadata.json
rabx-1.0.dist-info/RECORD
rabx-1.0.dist-info/top_level.txt
rabx-1.0.dist-info/WHEEL
