Metadata-Version: 2.0
Name: rabx
Version: 1.0
Summary: Routines for reading and writing RABX (RPC using Anything But XML)messages.
Home-page: https://github.com/mysociety/commonlib/tree/master/pylib/rabx
Author: mySociety
Author-email: matthew@mysociety.org
License: MIT
Platform: UNKNOWN
Classifier: Development Status :: 5 - Production/Stable
Classifier: License :: OSI Approved :: MIT License
Classifier: Intended Audience :: Developers
Classifier: Programming Language :: Python
Classifier: Programming Language :: Python :: 2
Classifier: Programming Language :: Python :: 3
Classifier: Topic :: Communications
Requires-Dist: six
